{"protocol":{"minReaderVersion":1,"minWriterVersion":2}}
{"metaData":{"id":"4b481360-d443-4dd5-898f-e1a6a1e21bc5","format":{"provider":"parquet","options":{}},"schemaString":"{\"type\":\"struct\",\"fields\":[{\"name\":\"FireID\",\"type\":\"string\",\"nullable\":true,\"metadata\":{}},{\"name\":\"DiscoveryDate\",\"type\":\"date\",\"nullable\":true,\"metadata\":{}},{\"name\":\"ContDate\",\"type\":\"date\",\"nullable\":true,\"metadata\":{}},{\"name\":\"Date\",\"type\":\"date\",\"nullable\":true,\"metadata\":{}},{\"name\":\"Latitude\",\"type\":\"double\",\"nullable\":true,\"metadata\":{}},{\"name\":\"Longitude\",\"type\":\"double\",\"nullable\":true,\"metadata\":{}}]}","partitionColumns":[],"configuration":{},"createdTime":1664106521848}}
{"txn":{"appId":"6b2fcbf4-b8c2-4b82-9ecc-c070c4006953","version":0,"lastUpdated":1664106524446}}
{"add":{"path":"part-00000-dd0d4e2f-a602-4b07-a0af-96d966118554-c000.snappy.parquet","partitionValues":{},"size":168355,"modificationTime":1664106524390,"dataChange":true,"stats":"{\"numRecords\":16644,\"minValues\":{\"FireID\":\"300000652\",\"DiscoveryDate\":\"2014-01-01\",\"ContDate\":\"2014-01-01\",\"Date\":\"2014-01-01\",\"Latitude\":17.96341,\"Longitude\":-155.2583},\"maxValues\":{\"FireID\":\"300347636\",\"DiscoveryDate\":\"2014-01-31\",\"ContDate\":\"2014-11-20\",\"Date\":\"2014-11-20\",\"Latitude\":48.56269,\"Longitude\":-67.19592},\"nullCount\":{\"FireID\":0,\"DiscoveryDate\":0,\"ContDate\":0,\"Date\":0,\"Latitude\":0,\"Longitude\":0}}"}}
{"commitInfo":{"timestamp":1664106524463,"operation":"STREAMING UPDATE","operationParameters":{"outputMode":"Append","queryId":"6b2fcbf4-b8c2-4b82-9ecc-c070c4006953","epochId":"0"},"isolationLevel":"Serializable","isBlindAppend":true,"operationMetrics":{"numRemovedFiles":"0","numAddedFiles":"1","numOutputRows":"16644","numOutputBytes":"168355"},"engineInfo":"Apache-Spark/3.3.0 Delta-Lake/2.1.0","txnId":"9a6e5e42-fa7d-421e-9c87-d3dc5714f8af"}}
